popgym/__init__.py
popgym/baselines/__init__.py
popgym/baselines/ppo.py
popgym/baselines/models/__init__.py
popgym/baselines/models/aggregations.py
popgym/baselines/models/embeddings.py
popgym/baselines/models/fwp.py
popgym/baselines/models/indrnn.py
popgym/baselines/models/linear_attention.py
popgym/baselines/models/lmu.py
popgym/baselines/models/s4d.py
popgym/baselines/ray_models/__init__.py
popgym/baselines/ray_models/base_model.py
popgym/baselines/ray_models/ray_diffnc.py
popgym/baselines/ray_models/ray_elman.py
popgym/baselines/ray_models/ray_frameconv.py
popgym/baselines/ray_models/ray_framestack.py
popgym/baselines/ray_models/ray_fwp.py
popgym/baselines/ray_models/ray_gru.py
popgym/baselines/ray_models/ray_indrnn.py
popgym/baselines/ray_models/ray_linear_attention.py
popgym/baselines/ray_models/ray_lmu.py
popgym/baselines/ray_models/ray_lstm.py
popgym/baselines/ray_models/ray_mlp.py
popgym/baselines/ray_models/ray_s4d.py
popgym/core/__init__.py
popgym/core/deck.py
popgym/core/env.py
popgym/core/maze.py
popgym/core/observability.py
popgym/core/wrapper.py
popgym/envs/__init__.py
popgym/envs/autoencode.py
popgym/envs/battleship.py
popgym/envs/concentration.py
popgym/envs/count_recall.py
popgym/envs/higher_lower.py
popgym/envs/labyrinth_escape.py
popgym/envs/labyrinth_explore.py
popgym/envs/minesweeper.py
popgym/envs/multiarmed_bandit.py
popgym/envs/noisy_position_only_cartpole.py
popgym/envs/noisy_position_only_pendulum.py
popgym/envs/position_only_cartpole.py
popgym/envs/position_only_pendulum.py
popgym/envs/repeat_first.py
popgym/envs/repeat_previous.py
popgym/envs/velocity_only_cartpole.py
popgym/util/__init__.py
popgym/util/benchmark.py
popgym/wrappers/__init__.py
popgym/wrappers/antialias.py
popgym/wrappers/discrete_action.py
popgym/wrappers/flatten.py
popgym/wrappers/markovian.py
popgym/wrappers/previous_action.py
tests/__init__.py
tests/base_env_test.py
tests/compute_framerate.py
tests/notest_bipedal_walker.py
tests/test_autoencode.py
popgym-1.0.6.dist-info/LICENSE.md
popgym-1.0.6.dist-info/METADATA
popgym-1.0.6.dist-info/WHEEL
popgym-1.0.6.dist-info/top_level.txt
popgym-1.0.6.dist-info/RECORD
