Metadata-Version: 2.1
Name: popgym
Version: 1.0.6
Summary: A collection of partially-observable procedural gym environments
Author: Steven Morad
License: MIT
Keywords: gym,gymnasium,pomdp,partially observable,reinforcement learning,rl
License-File: LICENSE.md
Requires-Dist: numpy
Requires-Dist: gymnasium
Provides-Extra: baselines
Requires-Dist: torch ; extra == 'baselines'
Requires-Dist: opt-einsum ; extra == 'baselines'
Requires-Dist: wandb ; extra == 'baselines'
Requires-Dist: dnc ; extra == 'baselines'
Requires-Dist: einops ; extra == 'baselines'
Requires-Dist: ray[rllib] ==2.3.0 ; extra == 'baselines'
Provides-Extra: navigation
Requires-Dist: mazelib ; extra == 'navigation'
